causalboundingengine/__init__.py
causalboundingengine/scenario.py
causalboundingengine/scenarios.py
causalboundingengine/algorithms/__init__.py
causalboundingengine/algorithms/algorithm.py
causalboundingengine/algorithms/autobound.py
causalboundingengine/algorithms/causaloptim.py
causalboundingengine/algorithms/entropybounds.py
causalboundingengine/algorithms/manski.py
causalboundingengine/algorithms/tianpearl.py
causalboundingengine/algorithms/zaffalonbounds.py
causalboundingengine/algorithms/zhangbareinboim.py
causalboundingengine/algorithms/autobound_pkg/setup.py
causalboundingengine/algorithms/autobound_pkg/autobound/DAG.py
causalboundingengine/algorithms/autobound_pkg/autobound/ID.py
causalboundingengine/algorithms/autobound_pkg/autobound/Parser.py
causalboundingengine/algorithms/autobound_pkg/autobound/Program.py
causalboundingengine/algorithms/autobound_pkg/autobound/Query.py
causalboundingengine/algorithms/autobound_pkg/autobound/SCM.py
causalboundingengine/algorithms/autobound_pkg/autobound/Simulation.py
causalboundingengine/algorithms/autobound_pkg/autobound/__init__.py
causalboundingengine/algorithms/autobound_pkg/autobound/bounds.py
causalboundingengine/algorithms/autobound_pkg/autobound/canonicalModel.py
causalboundingengine/algorithms/autobound_pkg/autobound/causalProblem.py
causalboundingengine/algorithms/autobound_pkg/autobound/funcs.py
causalboundingengine/algorithms/autobound_pkg/autobound/utils.py
causalboundingengine/algorithms/autobound_pkg/build/lib/autobound/DAG.py
causalboundingengine/algorithms/autobound_pkg/build/lib/autobound/ID.py
causalboundingengine/algorithms/autobound_pkg/build/lib/autobound/Parser.py
causalboundingengine/algorithms/autobound_pkg/build/lib/autobound/Program.py
causalboundingengine/algorithms/autobound_pkg/build/lib/autobound/Query.py
causalboundingengine/algorithms/autobound_pkg/build/lib/autobound/SCM.py
causalboundingengine/algorithms/autobound_pkg/build/lib/autobound/Simulation.py
causalboundingengine-0.1.5.dist-info/licenses/LICENSE
causalboundingengine-0.1.5.dist-info/METADATA
causalboundingengine-0.1.5.dist-info/WHEEL
causalboundingengine-0.1.5.dist-info/top_level.txt
causalboundingengine-0.1.5.dist-info/RECORD
