Metadata-Version: 2.4
Name: causalboundingengine
Version: 0.1.5
Summary: A framework for causal bounding algorithms
Author-email: Tobias Maringgele <tobias.maringgele@tum.de>
License: MIT License
Requires-Python: >=3.8
License-File: LICENSE
Requires-Dist: pandas
Requires-Dist: numpy
Requires-Dist: cvxpy
Requires-Dist: pulp
Requires-Dist: statsmodels
Requires-Dist: highspy
Requires-Dist: pyomo
Provides-Extra: r
Requires-Dist: rpy2; extra == "r"
Provides-Extra: java
Requires-Dist: jpype1; extra == "java"
Provides-Extra: full
Requires-Dist: rpy2; extra == "full"
Requires-Dist: jpype1; extra == "full"
Provides-Extra: docs
Requires-Dist: sphinx; extra == "docs"
Requires-Dist: sphinx_rtd_theme; extra == "docs"
Dynamic: license-file
